itk/TotalVariationPython.py
itk/_TotalVariationPython.pyd
itk/__init_totalvariation__.py
itk/itkProxTVImageFilterPython.py
itk/Configuration/TotalVariationConfig.py
itk/Configuration/TotalVariation_snake_case.py
itk_totalvariation-1.0.1.dist-info/licenses/LICENSE
itk_totalvariation.libs/msvcp140.dll
itk_totalvariation.libs/tbb12.dll
itk_totalvariation-1.0.1.dist-info/DELVEWHEEL
itk_totalvariation-1.0.1.dist-info/METADATA
itk_totalvariation-1.0.1.dist-info/WHEEL
itk_totalvariation-1.0.1.dist-info/RECORD
