Metadata-Version: 2.1
Name: itk-totalvariation
Version: 1.0.1
Summary: TotalVariation algorithms, providing a wrap for the external project: https://github.com/albarji/proxTV
Keywords: itk,InsightToolkit
Author-Email: Pablo Hernandez-Cerdan <pablo.hernandez.cerdan@outlook.com>
License:                                  Apache License
Classifier: Development Status :: 4 - Beta
Classifier: Intended Audience :: Developers
Classifier: Intended Audience :: Education
Classifier: Intended Audience :: Healthcare Industry
Classifier: Intended Audience :: Science/Research
Classifier: License :: OSI Approved :: Apache Software License
Classifier: Operating System :: Android
Classifier: Operating System :: MacOS
Classifier: Operating System :: Microsoft :: Windows
Classifier: Operating System :: POSIX
Classifier: Operating System :: Unix
Classifier: Programming Language :: C++
Classifier: Programming Language :: Python
Classifier: Topic :: Scientific/Engineering
Classifier: Topic :: Scientific/Engineering :: Information Analysis
Classifier: Topic :: Scientific/Engineering :: Medical Science Apps.
Classifier: Topic :: Software Development :: Libraries
Project-URL: Download, https://github.com/InsightSoftwareConsortium/ITKTotalVariation
Project-URL: Homepage, https://github.com/InsightSoftwareConsortium/ITKTotalVariation
Requires-Python: >=3.8
Requires-Dist: itk==5.4.*
